{
  "dict": {
    "site": {
      "subtitle": {
        "en": "Mystic, writer and creative consultant.",
        "pt": "Místico, escritor e consultor criativo."
      }
    },
    "home": {
      "welcome": {
        "en": "Welcome!",
        "pt": "Boas-vindas!"
      },
      "title": {
        "en": "My name is Fábio and I am a [pilgrim in the world](/en/about/) who also [writes](/en/blog/) and works as a [creative consultant.](/en/services/)",
        "pt": "Chamo-me Fábio e sou um [peregrino no mundo](/pt/quem-sou) que também [escreve](/pt/blog/) e trabalha como [consultor criativo.](/pt/servicos/)"
      },
      "contacts": {
        "en": "Keep in touch.",
        "pt": "Mantenha-se em contacto."
      }
    },
    "postlist": {
      "title": {
        "en": "Check out my latest posts.",
        "pt": "Leia os meus mais recentes artigos."
      },
      "link": {
        "en": "View all posts",
        "pt": "Veja todos os artigos"
      }
    },
    "postnav": {
      "title": {
        "en": "Keep on reading.",
        "pt": "Continue a ler."
      },
      "previous": {
        "en": "Previous Post:",
        "pt": "Artigo Anterior:"
      },
      "next": {
        "en": "Next Post:",
        "pt": "Artigo Seguinte:"
      }
    },
    "archive": {
      "permalink": {
        "en": "/en/blog",
        "pt": "/pt/blog"
      },
      "key": {
        "en": "Writings",
        "pt": "Artigos"
      },
      "title": {
        "en": "Selected writings",
        "pt": "Artigos seleccionados"
      },
      "subtitle": {
        "en": "Thoughts and essays about spirit, society, the Web and other media.",
        "pt": "Pensamentos e ensaios sobre o espírito, a sociedade, a Web e outros media."
      }
    },
    "subscribe": {
      "title": {
        "en": "Get updates in your inbox.",
        "pt": "Receba todas as novidades por correio electrónico."
      },
      "body": {
        "en": "Be the first to know about the latest posts and other resources.",
        "pt": "Fique a saber de novos artigos e outros recursos em primeira mão."
      },
      "link": {
        "en": "Sign up",
        "pt": "Subscreva já"
      }
    },
    "tag": {
      "link": {
        "en": "See all tags",
        "pt": "Ver todas as tags"
      }
    }
  }
}
